pyvis_inspector/__init__.py
pyvis_inspector/exceptions.py
pyvis_inspector/inferences.py
pyvis_inspector/setup.py
pyvis_inspector/tokens.py
pyvis_inspector-0.0.2.dist-info/METADATA
pyvis_inspector-0.0.2.dist-info/WHEEL
pyvis_inspector-0.0.2.dist-info/top_level.txt
pyvis_inspector-0.0.2.dist-info/RECORD
