Metadata-Version: 2.1
Name: pyvis-inspector
Version: 0.0.2
Summary: A simple python wrapper for the IBM Vision Service API
Home-page: https://github.com/Vern-Technologies/pyvis-inspector
Author: Matthew Ashley
Author-email: matthewashley@verntechnologies.com
License: MIT
Platform: UNKNOWN
Classifier: Programming Language :: Python :: 3
Classifier: License :: OSI Approved :: MIT License
Classifier: Operating System :: OS Independent
Requires-Python: >=3.7
Requires-Dist: requests
